betterosi/__init__.py
betterosi/io.py
betterosi/osi2mcap.py
betterosi/viewer.py
betterosi/generated/__init__.py
betterosi/generated/google_proto_descriptor_pool.py
betterosi/generated/message_pool.py
betterosi/generated/py.typed
betterosi/generated/google/__init__.py
betterosi/generated/google/protobuf/__init__.py
betterosi/generated/google/protobuf/compiler/__init__.py
betterosi/generated/osi3/__init__.py
betterosi-0.8.4.dist-info/METADATA
betterosi-0.8.4.dist-info/WHEEL
betterosi-0.8.4.dist-info/entry_points.txt
betterosi-0.8.4.dist-info/licenses/LICENSE
betterosi-0.8.4.dist-info/RECORD
