Metadata-Version: 2.4
Name: betterosi
Version: 0.8.4
Summary: betterosi - a python library for reading and writing open-simulation-interface files using betterproto2
Project-URL: Homepage, https://github.com/ika-rwth-aachen/betterosi
Project-URL: Repository, https://github.com/ika-rwth-aachen/betterosi
Author-email: ika - RWTH Aachen <michael.schuldes@ika.rwth-aachen.de>
License: MPL-2.0
License-File: LICENSE
Keywords: automated-driving,open-simulation-interface,osi,simulation
Classifier: License :: OSI Approved :: Mozilla Public License 2.0 (MPL 2.0)
Classifier: Operating System :: OS Independent
Classifier: Programming Language :: Python :: 3
Classifier: Programming Language :: Python :: 3.10
Classifier: Programming Language :: Python :: 3.11
Classifier: Programming Language :: Python :: 3.12
Requires-Python: >=3.10
Requires-Dist: betterproto2-compiler
Requires-Dist: betterproto2-rust-codec
Requires-Dist: betterproto2[all]
Requires-Dist: matplotlib
Requires-Dist: mcap
Requires-Dist: mcap-protobuf-support
Requires-Dist: numpy
Requires-Dist: tqdm
Requires-Dist: typer
Provides-Extra: test
Requires-Dist: pre-commit; extra == 'test'
Requires-Dist: pytest; extra == 'test'
Requires-Dist: pytest-codeblocks; extra == 'test'
Requires-Dist: pytest-cov; extra == 'test'
Requires-Dist: pytest-env; extra == 'test'
Requires-Dist: pytest-progress; extra == 'test'
Requires-Dist: pytest-sugar; extra == 'test'
Requires-Dist: ruff; extra == 'test'
